Django_auths/__init__.py
Django_auths/module_auth.py
Django_auths/slaveni/db.sqlite3
Django_auths/slaveni/manage.py
Django_auths/slaveni/package.json
Django_auths/slaveni/app/migrations/__pycache__/0001_initial.cpython-312.pyc
Django_auths/slaveni/app/migrations/__pycache__/0001_initial.cpython-313.pyc
Django_auths/slaveni/app/migrations/__pycache__/0002_rename_cancellation_reason_request_other_service_description.cpython-312.pyc
Django_auths/slaveni/app/migrations/__pycache__/0002_rename_cancellation_reason_request_other_service_description.cpython-313.pyc
Django_auths/slaveni/app/migrations/__pycache__/0003_request_status_cancel.cpython-312.pyc
Django_auths/slaveni/app/migrations/__pycache__/0003_request_status_cancel.cpython-313.pyc
Django_auths/slaveni/app/migrations/__pycache__/__init__.cpython-312.pyc
Django_auths/slaveni/app/migrations/__pycache__/__init__.cpython-313.pyc
Django_auths/slaveni/app/static/css/styles.css
Django_auths/slaveni/app/static/js/scripts.js
django_users_logins-0.1.1.dist-info/METADATA
django_users_logins-0.1.1.dist-info/WHEEL
django_users_logins-0.1.1.dist-info/top_level.txt
django_users_logins-0.1.1.dist-info/RECORD
